utube_search/__init__.py
utube_search/api.py
utube_search/cli.py
utube_search/config.py
utube_search/exceptions.py
utube_search/search.py
utube_search-0.1.0.dist-info/entry_points.txt
utube_search-0.1.0.dist-info/LICENSE
utube_search-0.1.0.dist-info/WHEEL
utube_search-0.1.0.dist-info/METADATA
utube_search-0.1.0.dist-info/RECORD
